{
    "rank": "39",
    "pokemon": "サンダー",
    "same_team": {
        "1": "オーガポン",
        "2": "ハバタクカミ",
        "3": "ウーラオス",
        "4": "カイリュー",
        "5": "ハッサム",
        "6": "サーフゴー",
        "7": "パオジアン",
        "8": "ラティオス",
        "9": "ポリゴン２",
        "10": "ガチグマ"
    },
    "dominant": {
        "1": "ウーラオス",
        "2": "オーガポン",
        "3": "カイリュー",
        "4": "ハッサム",
        "5": "ハバタクカミ",
        "6": "ランドロス",
        "7": "サーフゴー",
        "8": "パオジアン",
        "9": "ガチグマ",
        "10": "ペリッパー"
    },
    "disadvantage": {
        "1": "オーガポン",
        "2": "ハバタクカミ",
        "3": "カイリュー",
        "4": "ウーラオス",
        "5": "ラティオス",
        "6": "ガチグマ",
        "7": "パオジアン",
        "8": "ウガツホムラ",
        "9": "ウーラオス",
        "10": "サーフゴー"
    }
}