{
    "rank": "82",
    "pokemon": "ハピナス",
    "same_team": {
        "1": "ヘイラッシャ",
        "2": "ドヒドイデ",
        "3": "ラウドボーン",
        "4": "グライオン",
        "5": "クレベース",
        "6": "カイリュー",
        "7": "テツノツツミ",
        "8": "キョジオーン",
        "9": "エアームド",
        "10": "ポリゴン２"
    },
    "dominant": {
        "1": "サーフゴー",
        "2": "ハバタクカミ",
        "3": "ハッサム",
        "4": "ジャローダ",
        "5": "テツノツツミ",
        "6": "ガチグマ",
        "7": "ラティオス",
        "8": "カイリュー",
        "9": "パオジアン",
        "10": "ブリジュラス"
    },
    "disadvantage": {
        "1": "オーガポン",
        "2": "サーフゴー",
        "3": "カイリュー",
        "4": "ハバタクカミ",
        "5": "ラティオス",
        "6": "パオジアン",
        "7": "ウーラオス",
        "8": "ブリジュラス",
        "9": "ジャローダ",
        "10": "ウーラオス"
    }
}